odoo/addons/contract_invoice_start_end_dates/README.rst
odoo/addons/contract_invoice_start_end_dates/__init__.py
odoo/addons/contract_invoice_start_end_dates/__manifest__.py
odoo/addons/contract_invoice_start_end_dates/i18n/contract_invoice_start_end_dates.pot
odoo/addons/contract_invoice_start_end_dates/i18n/da.po
odoo/addons/contract_invoice_start_end_dates/i18n/es.po
odoo/addons/contract_invoice_start_end_dates/i18n/it.po
odoo/addons/contract_invoice_start_end_dates/models/__init__.py
odoo/addons/contract_invoice_start_end_dates/models/contract_line.py
odoo/addons/contract_invoice_start_end_dates/readme/CONTRIBUTORS.rst
odoo/addons/contract_invoice_start_end_dates/readme/DESCRIPTION.rst
odoo/addons/contract_invoice_start_end_dates/static/description/icon.png
odoo/addons/contract_invoice_start_end_dates/static/description/index.html
odoo/addons/contract_invoice_start_end_dates/tests/__init__.py
odoo/addons/contract_invoice_start_end_dates/tests/test_contract_invoice_start_end_dates.py
odoo14_addon_contract_invoice_start_end_dates-14.0.1.0.1.dev10.dist-info/METADATA
odoo14_addon_contract_invoice_start_end_dates-14.0.1.0.1.dev10.dist-info/WHEEL
odoo14_addon_contract_invoice_start_end_dates-14.0.1.0.1.dev10.dist-info/top_level.txt
odoo14_addon_contract_invoice_start_end_dates-14.0.1.0.1.dev10.dist-info/RECORD
