Metadata-Version: 2.1
Name: odoo14-addon-contract_invoice_start_end_dates
Version: 14.0.1.0.1.dev10
Summary: Contract Invoice Start End Dates
Home-page: https://github.com/OCA/contract
Author: Akretion, Odoo Community Association (OCA)
Author-email: support@odoo-community.org
License: AGPL-3
Classifier: Programming Language :: Python
Classifier: Framework :: Odoo
Classifier: Framework :: Odoo :: 14.0
Classifier: License :: OSI Approved :: GNU Affero General Public License v3
Requires-Python: >=3.6
Requires-Dist: odoo14-addon-account-invoice-start-end-dates
Requires-Dist: odoo14-addon-contract
Requires-Dist: odoo<14.1dev,>=14.0a
